kisa_utils/__init__.py
kisa_utils/cache.py
kisa_utils/codes.py
kisa_utils/config.py
kisa_utils/dataStructures.py
kisa_utils/dates.py
kisa_utils/db.py
kisa_utils/encryption.py
kisa_utils/figures.py
kisa_utils/functionUtils.py
kisa_utils/log.py
kisa_utils/remote.py
kisa_utils/response.py
kisa_utils/score.py
kisa_utils/standardize.py
kisa_utils/storage.py
kisa_utils/threads.py
kisa_utils/token.py
kisa_utils/permissions/__config__.py
kisa_utils/permissions/__init__.py
kisa_utils/queues/__init__.py
kisa_utils/queues/persistent.py
kisa_utils/queues/callables/__init__.py
kisa_utils/queues/callables/enqueueFunctionCalls.py
kisa_utils/queues/callables/executorQueues.py
kisa_utils/servers/__init__.py
kisa_utils/servers/flask.py
kisa_utils/structures/__init__.py
kisa_utils/structures/utils.py
kisa_utils/structures/validator.py
kisa_utils-0.43.1.dist-info/METADATA
kisa_utils-0.43.1.dist-info/WHEEL
kisa_utils-0.43.1.dist-info/top_level.txt
kisa_utils-0.43.1.dist-info/RECORD
