Metadata-Version: 2.1
Name: kisa-utils
Version: 0.43.1
Summary: Utility functions and modules for KISA Developers
Author: Tom Bukenya
Author-email: glayn2bukman@gmail.com
Classifier: Programming Language :: Python :: 3
Classifier: License :: OSI Approved :: MIT License
Classifier: Operating System :: OS Independent
Requires-Python: >=3.10
Requires-Dist: requests >=2.31.0
Requires-Dist: Flask >=2.3.2
Requires-Dist: Flask-BasicAuth >=0.2.0
Requires-Dist: Flask-Cors >=4.0.0
